hitsquad/__init__.py
hitsquad/hitsquad.py
hitsquad/sshpass
hitsquad-0.2.1.dist-info/LICENSE
hitsquad-0.2.1.dist-info/METADATA
hitsquad-0.2.1.dist-info/WHEEL
hitsquad-0.2.1.dist-info/entry_points.txt
hitsquad-0.2.1.dist-info/top_level.txt
hitsquad-0.2.1.dist-info/RECORD
