Metadata-Version: 2.1
Name: hitsquad
Version: 0.2.1
Summary: GGWP command broadcast over ssh
Home-page: https://github.com/pypa/sampleproject
Author: Shubham Arawkar
Author-email: arawkar.shubham08@gmail.com
License: UNKNOWN
Platform: UNKNOWN
Classifier: Programming Language :: Python :: 3
Classifier: License :: OSI Approved :: MIT License
Classifier: Operating System :: OS Independent
Requires-Python: >=3.5
Requires-Dist: argparse
